{
  "version": "2.4.0",
  "flags": {},
  "shapes": [
    {
      "label": "resistor",
      "score": 0.9697180986404419,
      "points": [
        [
          369.9778363108635,
          274.94147349894047
        ],
        [
          398.81845396757126,
          274.94147349894047
        ],
        [
          398.81845396757126,
          340.0822929739952
        ],
        [
          369.9778363108635,
          340.0822929739952
        ]
      ],
      "group_id": 0,
      "description": null,
      "difficult": false,
      "shape_type": "rectangle",
      "flags": {},
      "attributes": {},
      "kie_linking": []
    },
    {
      "label": "Positive",
      "score": 0.99993896484375,
      "points": [
        [
          383.0,
          276.0
        ]
      ],
      "group_id": 0,
      "description": null,
      "difficult": false,
      "shape_type": "point",
      "flags": {},
      "attributes": {},
      "kie_linking": []
    },
    {
      "label": "Negative",
      "score": 0.9999487400054932,
      "points": [
        [
          382.0,
          335.0
        ]
      ],
      "group_id": 0,
      "description": null,
      "difficult": false,
      "shape_type": "point",
      "flags": {},
      "attributes": {},
      "kie_linking": []
    },
    {
      "label": "resistor",
      "score": 0.9668258428573608,
      "points": [
        [
          604.0431336164474,
          918.9994168281555
        ],
        [
          633.4833987951279,
          918.9994168281555
        ],
        [
          633.4833987951279,
          983.7257187366486
        ],
        [
          604.0431336164474,
          983.7257187366486
        ]
      ],
      "group_id": 1,
      "description": null,
      "difficult": false,
      "shape_type": "rectangle",
      "flags": {},
      "attributes": {},
      "kie_linking": []
    },
    {
      "label": "Positive",
      "score": 0.999525785446167,
      "points": [
        [
          617.4407582938389,
          920.7985781990521
        ]
      ],
      "group_id": 1,
      "description": null,
      "difficult": false,
      "shape_type": "point",
      "flags": {},
      "attributes": {},
      "kie_linking": []
    },
    {
      "label": "Negative",
      "score": 0.9998757839202881,
      "points": [
        [
          616.0,
          978.0
        ]
      ],
      "group_id": 1,
      "description": null,
      "difficult": false,
      "shape_type": "point",
      "flags": {},
      "attributes": {},
      "kie_linking": []
    },
    {
      "label": "capacitor",
      "score": 0.9628875255584717,
      "points": [
        [
          747.8016988635063,
          920.0342838764191
        ],
        [
          798.4946123957634,
          920.0342838764191
        ],
        [
          798.4946123957634,
          947.1418093442917
        ],
        [
          747.8016988635063,
          947.1418093442917
        ]
      ],
      "group_id": 2,
      "description": null,
      "difficult": false,
      "shape_type": "rectangle",
      "flags": {},
      "attributes": {},
      "kie_linking": []
    },
    {
      "label": "Positive",
      "score": 0.9997787475585938,
      "points": [
        [
          774.3127962085309,
          924.1161137440758
        ]
      ],
      "group_id": 2,
      "description": null,
      "difficult": false,
      "shape_type": "point",
      "flags": {},
      "attributes": {},
      "kie_linking": []
    },
    {
      "label": "Negative",
      "score": 0.9998490810394287,
      "points": [
        [
          773.3649289099527,
          940.2298578199052
        ]
      ],
      "group_id": 2,
      "description": null,
      "difficult": false,
      "shape_type": "point",
      "flags": {},
      "attributes": {},
      "kie_linking": []
    },
    {
      "label": "resistor",
      "score": 0.9620842337608337,
      "points": [
        [
          438.74430298805237,
          575.6054041385651
        ],
        [
          502.92427110671997,
          575.6054041385651
        ],
        [
          502.92427110671997,
          606.7749345302582
        ],
        [
          438.74430298805237,
          606.7749345302582
        ]
      ],
      "group_id": 3,
      "description": null,
      "difficult": false,
      "shape_type": "rectangle",
      "flags": {},
      "attributes": {},
      "kie_linking": []
    },
    {
      "label": "Positive",
      "score": 0.9999876022338867,
      "points": [
        [
          441.13744075829385,
          590.4668246445498
        ]
      ],
      "group_id": 3,
      "description": null,
      "difficult": false,
      "shape_type": "point",
      "flags": {},
      "attributes": {},
      "kie_linking": []
    },
    {
      "label": "Negative",
      "score": 0.9999898672103882,
      "points": [
        [
          499.4312796208531,
          589.0450236966825
        ]
      ],
      "group_id": 3,
      "description": null,
      "difficult": false,
      "shape_type": "point",
      "flags": {},
      "attributes": {},
      "kie_linking": []
    },
    {
      "label": "capacitor",
      "score": 0.9602805376052856,
      "points": [
        [
          338.51831352710724,
          666.197113931179
        ],
        [
          388.82694590091705,
          666.197113931179
        ],
        [
          388.82694590091705,
          692.8397278189659
        ],
        [
          338.51831352710724,
          692.8397278189659
        ]
      ],
      "group_id": 4,
      "description": null,
      "difficult": false,
      "shape_type": "rectangle",
      "flags": {},
      "attributes": {},
      "kie_linking": []
    },
    {
      "label": "Positive",
      "score": 0.999904990196228,
      "points": [
        [
          362.93838862559244,
          668.6658767772512
        ]
      ],
      "group_id": 4,
      "description": null,
      "difficult": false,
      "shape_type": "point",
      "flags": {},
      "attributes": {},
      "kie_linking": []
    },
    {
      "label": "Negative",
      "score": 0.9999517798423767,
      "points": [
        [
          362.93838862559244,
          688.5710900473933
        ]
      ],
      "group_id": 4,
      "description": null,
      "difficult": false,
      "shape_type": "point",
      "flags": {},
      "attributes": {},
      "kie_linking": []
    },
    {
      "label": "resistor",
      "score": 0.9578686952590942,
      "points": [
        [
          604.0778403282166,
          275.2570835351944
        ],
        [
          633.0425047874451,
          275.2570835351944
        ],
        [
          633.0425047874451,
          339.47499150037766
        ],
        [
          604.0778403282166,
          339.47499150037766
        ]
      ],
      "group_id": 5,
      "description": null,
      "difficult": false,
      "shape_type": "rectangle",
      "flags": {},
      "attributes": {},
      "kie_linking": []
    },
    {
      "label": "Positive",
      "score": 0.9998742341995239,
      "points": [
        [
          618.3886255924172,
          277.67061611374413
        ]
      ],
      "group_id": 5,
      "description": null,
      "difficult": false,
      "shape_type": "point",
      "flags": {},
      "attributes": {},
      "kie_linking": []
    },
    {
      "label": "Negative",
      "score": 0.999983549118042,
      "points": [
        [
          617.914691943128,
          337.38625592417065
        ]
      ],
      "group_id": 5,
      "description": null,
      "difficult": false,
      "shape_type": "point",
      "flags": {},
      "attributes": {},
      "kie_linking": []
    },
    {
      "label": "resistor",
      "score": 0.9523136615753174,
      "points": [
        [
          224.03439778089523,
          752.7875225543976
        ],
        [
          288.14983516931534,
          752.7875225543976
        ],
        [
          288.14983516931534,
          781.315911769867
        ],
        [
          224.03439778089523,
          781.315911769867
        ]
      ],
      "group_id": 6,
      "description": null,
      "difficult": false,
      "shape_type": "rectangle",
      "flags": {},
      "attributes": {},
      "kie_linking": []
    },
    {
      "label": "Negative",
      "score": 0.9999876022338867,
      "points": [
        [
          284.73933649289097,
          766.2962085308056
        ]
      ],
      "group_id": 6,
      "description": null,
      "difficult": false,
      "shape_type": "point",
      "flags": {},
      "attributes": {},
      "kie_linking": []
    },
    {
      "label": "gnd",
      "score": 0.952257513999939,
      "points": [
        [
          593.5357096195221,
          1072.264783859253
        ],
        [
          641.2850189208984,
          1072.264783859253
        ],
        [
          641.2850189208984,
          1096.2068724632263
        ],
        [
          593.5357096195221,
          1096.2068724632263
        ]
      ],
      "group_id": 7,
      "description": null,
      "difficult": false,
      "shape_type": "rectangle",
      "flags": {},
      "attributes": {},
      "kie_linking": []
    },
    {
      "label": "port",
      "score": 0.9999785423278809,
      "points": [
        [
          616.9668246445499,
          1073.4052132701422
        ]
      ],
      "group_id": 7,
      "description": null,
      "difficult": false,
      "shape_type": "point",
      "flags": {},
      "attributes": {},
      "kie_linking": []
    },
    {
      "label": "resistor",
      "score": 0.949350118637085,
      "points": [
        [
          145.81553176045418,
          167.06742131710052
        ],
        [
          209.80025812983513,
          167.06742131710052
        ],
        [
          209.80025812983513,
          195.8978117108345
        ],
        [
          145.81553176045418,
          195.8978117108345
        ]
      ],
      "group_id": 8,
      "description": null,
      "difficult": false,
      "shape_type": "rectangle",
      "flags": {},
      "attributes": {},
      "kie_linking": []
    },
    {
      "label": "Positive",
      "score": 0.9998077154159546,
      "points": [
        [
          147.0,
          179.0
        ]
      ],
      "group_id": 8,
      "description": null,
      "difficult": false,
      "shape_type": "point",
      "flags": {},
      "attributes": {},
      "kie_linking": []
    },
    {
      "label": "Negative",
      "score": 0.9998339414596558,
      "points": [
        [
          205.0,
          179.0
        ]
      ],
      "group_id": 8,
      "description": null,
      "difficult": false,
      "shape_type": "point",
      "flags": {},
      "attributes": {},
      "kie_linking": []
    },
    {
      "label": "capacitor",
      "score": 0.9409525394439697,
      "points": [
        [
          240.74482172727585,
          295.17510706186295
        ],
        [
          290.60239881277084,
          295.17510706186295
        ],
        [
          290.60239881277084,
          322.8694134950638
        ],
        [
          240.74482172727585,
          322.8694134950638
        ]
      ],
      "group_id": 9,
      "description": null,
      "difficult": false,
      "shape_type": "rectangle",
      "flags": {},
      "attributes": {},
      "kie_linking": []
    },
    {
      "label": "Positive",
      "score": 0.9999847412109375,
      "points": [
        [
          266.7298578199052,
          299.9454976303318
        ]
      ],
      "group_id": 9,
      "description": null,
      "difficult": false,
      "shape_type": "point",
      "flags": {},
      "attributes": {},
      "kie_linking": []
    },
    {
      "label": "Negative",
      "score": 0.9999978542327881,
      "points": [
        [
          265.0,
          315.0
        ]
      ],
      "group_id": 9,
      "description": null,
      "difficult": false,
      "shape_type": "point",
      "flags": {},
      "attributes": {},
      "kie_linking": []
    },
    {
      "label": "nmos",
      "score": 0.7902895212173462,
      "points": [
        [
          578.1042654028437,
          153.2804769873619
        ],
        [
          622.8108209967613,
          153.2804769873619
        ],
        [
          622.8108209967613,
          212.26777251184834
        ],
        [
          578.1042654028437,
          212.26777251184834
        ]
      ],
      "group_id": 10,
      "description": null,
      "difficult": false,
      "shape_type": "rectangle",
      "flags": {},
      "attributes": {},
      "kie_linking": []
    },
    {
      "label": "Drain",
      "score": 0.9992526769638062,
      "points": [
        [
          615.0,
          160.0
        ]
      ],
      "group_id": 10,
      "description": null,
      "difficult": false,
      "shape_type": "point",
      "flags": {},
      "attributes": {},
      "kie_linking": []
    },
    {
      "label": "Source",
      "score": 0.9992387294769287,
      "points": [
        [
          616.0,
          201.0
        ]
      ],
      "group_id": 10,
      "description": null,
      "difficult": false,
      "shape_type": "point",
      "flags": {},
      "attributes": {},
      "kie_linking": []
    },
    {
      "label": "Gate",
      "score": 0.9927096366882324,
      "points": [
        [
          589.9526066350711,
          181.46208530805688
        ]
      ],
      "group_id": 10,
      "description": null,
      "difficult": false,
      "shape_type": "point",
      "flags": {},
      "attributes": {},
      "kie_linking": []
    },
    {
      "label": "Positive",
      "score": null,
      "points": [
        [
          225.49763033175356,
          765.8222748815166
        ]
      ],
      "group_id": null,
      "description": "",
      "difficult": false,
      "shape_type": "point",
      "flags": {},
      "attributes": {},
      "kie_linking": []
    },
    {
      "label": "nmos",
      "score": null,
      "points": [
        [
          575.7345971563982,
          737.8601895734597
        ],
        [
          623.6018957345972,
          737.8601895734597
        ],
        [
          623.6018957345972,
          798.5236966824644
        ],
        [
          575.7345971563982,
          798.5236966824644
        ]
      ],
      "group_id": null,
      "description": "",
      "difficult": false,
      "shape_type": "rectangle",
      "flags": {},
      "attributes": {},
      "kie_linking": []
    },
    {
      "label": "Gate",
      "score": null,
      "points": [
        [
          592.7962085308058,
          765.8222748815166
        ]
      ],
      "group_id": null,
      "description": "",
      "difficult": false,
      "shape_type": "point",
      "flags": {},
      "attributes": {},
      "kie_linking": []
    },
    {
      "label": "Source",
      "score": null,
      "points": [
        [
          617.4407582938389,
          783.8317535545024
        ]
      ],
      "group_id": null,
      "description": "",
      "difficult": false,
      "shape_type": "point",
      "flags": {},
      "attributes": {},
      "kie_linking": []
    },
    {
      "label": "Gate",
      "score": null,
      "points": [
        [
          617.914691943128,
          745.4431279620853
        ]
      ],
      "group_id": null,
      "description": "",
      "difficult": false,
      "shape_type": "point",
      "flags": {},
      "attributes": {},
      "kie_linking": []
    }
  ],
  "imagePath": "1204.png",
  "imageData": null,
  "imageHeight": 1107,
  "imageWidth": 860,
  "text": ""
}