{
    "version": "5.1.1",
    "flags": {},
    "shapes": [
        {
            "label": "resistor2",
            "points": [
                [
                    560.0,
                    117.0
                ],
                [
                    591.0,
                    117.0
                ],
                [
                    591.0,
                    133.0
                ],
                [
                    560.0,
                    133.0
                ]
            ],
            "group_id": 0,
            "shape_type": "rectangle",
            "flags": {}
        },
        {
            "label": "npn",
            "points": [
                [
                    305.0,
                    215.0
                ],
                [
                    330.0,
                    215.0
                ],
                [
                    330.0,
                    240.0
                ],
                [
                    305.0,
                    240.0
                ]
            ],
            "group_id": 1,
            "shape_type": "rectangle",
            "flags": {}
        },
        {
            "label": "gnd",
            "points": [
                [
                    284.0,
                    301.0
                ],
                [
                    297.0,
                    301.0
                ],
                [
                    297.0,
                    307.0
                ],
                [
                    284.0,
                    307.0
                ]
            ],
            "group_id": 2,
            "shape_type": "rectangle",
            "flags": {}
        },
        {
            "label": "resistor2",
            "points": [
                [
                    480.2013,
                    213.2951
                ],
                [
                    494.8026,
                    213.2951
                ],
                [
                    494.8026,
                    243.0
                ],
                [
                    480.2013,
                    243.0
                ]
            ],
            "group_id": 3,
            "shape_type": "rectangle",
            "flags": {}
        },
        {
            "label": "pnp",
            "points": [
                [
                    172.0,
                    359.0
                ],
                [
                    198.0,
                    359.0
                ],
                [
                    198.0,
                    386.0
                ],
                [
                    172.0,
                    386.0
                ]
            ],
            "group_id": 4,
            "shape_type": "rectangle",
            "flags": {}
        },
        {
            "label": "resistor2",
            "points": [
                [
                    283.0,
                    258.0
                ],
                [
                    298.0,
                    258.0
                ],
                [
                    298.0,
                    288.0
                ],
                [
                    283.0,
                    288.0
                ]
            ],
            "group_id": 5,
            "shape_type": "rectangle",
            "flags": {}
        },
        {
            "label": "resistor2",
            "points": [
                [
                    75.0,
                    386.2068
                ],
                [
                    88.0,
                    386.2068
                ],
                [
                    88.0,
                    416.0
                ],
                [
                    75.0,
                    416.0
                ]
            ],
            "group_id": 6,
            "shape_type": "rectangle",
            "flags": {}
        },
        {
            "label": "resistor2",
            "points": [
                [
                    334.6387,
                    68.7048
                ],
                [
                    363.1047,
                    68.7048
                ],
                [
                    363.1047,
                    83.83
                ],
                [
                    334.6387,
                    83.83
                ]
            ],
            "group_id": 7,
            "shape_type": "rectangle",
            "flags": {}
        },
        {
            "label": "gnd",
            "points": [
                [
                    179.0,
                    397.0
                ],
                [
                    192.0,
                    397.0
                ],
                [
                    192.0,
                    403.0
                ],
                [
                    179.0,
                    403.0
                ]
            ],
            "group_id": 8,
            "shape_type": "rectangle",
            "flags": {}
        },
        {
            "label": "resistor2",
            "points": [
                [
                    319.0,
                    107.0
                ],
                [
                    334.0,
                    107.0
                ],
                [
                    334.0,
                    136.0
                ],
                [
                    319.0,
                    136.0
                ]
            ],
            "group_id": 9,
            "shape_type": "rectangle",
            "flags": {}
        },
        {
            "label": "resistor2",
            "points": [
                [
                    99.0,
                    265.0
                ],
                [
                    130.0,
                    265.0
                ],
                [
                    130.0,
                    281.0
                ],
                [
                    99.0,
                    281.0
                ]
            ],
            "group_id": 10,
            "shape_type": "rectangle",
            "flags": {}
        },
        {
            "label": "npn",
            "points": [
                [
                    253.0,
                    370.0
                ],
                [
                    280.0,
                    370.0
                ],
                [
                    280.0,
                    397.0
                ],
                [
                    253.0,
                    397.0
                ]
            ],
            "group_id": 11,
            "shape_type": "rectangle",
            "flags": {}
        },
        {
            "label": "gnd",
            "points": [
                [
                    395.0,
                    301.0
                ],
                [
                    409.0,
                    301.0
                ],
                [
                    409.0,
                    307.0
                ],
                [
                    395.0,
                    307.0
                ]
            ],
            "group_id": 12,
            "shape_type": "rectangle",
            "flags": {}
        },
        {
            "label": "resistor2",
            "points": [
                [
                    232.0,
                    219.0
                ],
                [
                    263.0,
                    219.0
                ],
                [
                    263.0,
                    237.0
                ],
                [
                    232.0,
                    237.0
                ]
            ],
            "group_id": 13,
            "shape_type": "rectangle",
            "flags": {}
        },
        {
            "label": "resistor2",
            "points": [
                [
                    364.0,
                    107.0
                ],
                [
                    380.0,
                    107.0
                ],
                [
                    380.0,
                    137.0
                ],
                [
                    364.0,
                    137.0
                ]
            ],
            "group_id": 14,
            "shape_type": "rectangle",
            "flags": {}
        },
        {
            "label": "gnd",
            "points": [
                [
                    141.0,
                    208.0
                ],
                [
                    154.0,
                    208.0
                ],
                [
                    154.0,
                    214.0
                ],
                [
                    141.0,
                    214.0
                ]
            ],
            "group_id": 15,
            "shape_type": "rectangle",
            "flags": {}
        },
        {
            "label": "npn",
            "points": [
                [
                    367.0,
                    215.0
                ],
                [
                    393.0,
                    215.0
                ],
                [
                    393.0,
                    241.0
                ],
                [
                    367.0,
                    241.0
                ]
            ],
            "group_id": 16,
            "shape_type": "rectangle",
            "flags": {}
        },
        {
            "label": "resistor2",
            "points": [
                [
                    518.0,
                    213.0
                ],
                [
                    533.0,
                    213.0
                ],
                [
                    533.0,
                    243.0
                ],
                [
                    518.0,
                    243.0
                ]
            ],
            "group_id": 17,
            "shape_type": "rectangle",
            "flags": {}
        },
        {
            "label": "resistor2",
            "points": [
                [
                    430.0,
                    220.0
                ],
                [
                    459.0,
                    220.0
                ],
                [
                    459.0,
                    236.0
                ],
                [
                    430.0,
                    236.0
                ]
            ],
            "group_id": 18,
            "shape_type": "rectangle",
            "flags": {}
        },
        {
            "label": "resistor2",
            "points": [
                [
                    394.0,
                    258.0
                ],
                [
                    409.0,
                    258.0
                ],
                [
                    409.0,
                    288.0
                ],
                [
                    394.0,
                    288.0
                ]
            ],
            "group_id": 19,
            "shape_type": "rectangle",
            "flags": {}
        },
        {
            "label": "resistor2",
            "points": [
                [
                    641.0,
                    164.0
                ],
                [
                    671.0,
                    164.0
                ],
                [
                    671.0,
                    181.0
                ],
                [
                    641.0,
                    181.0
                ]
            ],
            "group_id": 20,
            "shape_type": "rectangle",
            "flags": {}
        },
        {
            "label": "capacitor",
            "points": [
                [
                    121.0,
                    99.0
                ],
                [
                    132.0,
                    99.0
                ],
                [
                    132.0,
                    113.0
                ],
                [
                    121.0,
                    113.0
                ]
            ],
            "group_id": 21,
            "shape_type": "rectangle",
            "flags": {}
        },
        {
            "label": "npn",
            "points": [
                [
                    326.0,
                    370.0
                ],
                [
                    353.0,
                    370.0
                ],
                [
                    353.0,
                    399.0
                ],
                [
                    326.0,
                    399.0
                ]
            ],
            "group_id": 22,
            "shape_type": "rectangle",
            "flags": {}
        },
        {
            "label": "gnd",
            "points": [
                [
                    76.0,
                    432.0
                ],
                [
                    89.0,
                    432.0
                ],
                [
                    89.0,
                    438.0
                ],
                [
                    76.0,
                    438.0
                ]
            ],
            "group_id": 23,
            "shape_type": "rectangle",
            "flags": {}
        },
        {
            "label": "resistor2",
            "points": [
                [
                    101.0,
                    357.0
                ],
                [
                    129.0,
                    357.0
                ],
                [
                    129.0,
                    372.0
                ],
                [
                    101.0,
                    372.0
                ]
            ],
            "group_id": 24,
            "shape_type": "rectangle",
            "flags": {}
        },
        {
            "label": "Diso_amp",
            "points": [
                [
                    544.0,
                    145.0
                ],
                [
                    601.0,
                    145.0
                ],
                [
                    601.0,
                    200.0
                ],
                [
                    544.0,
                    200.0
                ]
            ],
            "group_id": 25,
            "shape_type": "rectangle",
            "flags": {}
        },
        {
            "label": "resistor2",
            "points": [
                [
                    73.4611,
                    342.9661
                ],
                [
                    90.4374,
                    342.9661
                ],
                [
                    90.4374,
                    374.6923
                ],
                [
                    73.4611,
                    374.6923
                ]
            ],
            "group_id": 26,
            "shape_type": "rectangle",
            "flags": {}
        },
        {
            "label": "resistor2",
            "points": [
                [
                    139.3292,
                    163.7726
                ],
                [
                    156.3048,
                    163.7726
                ],
                [
                    156.3048,
                    195.5049
                ],
                [
                    139.3292,
                    195.5049
                ]
            ],
            "group_id": 27,
            "shape_type": "rectangle",
            "flags": {}
        },
        {
            "label": "corner",
            "score": 0.7864032983779907,
            "points": [
                [
                    398.02480745315546,
                    223.2808263301849
                ],
                [
                    406.2347817420959,
                    223.2808263301849
                ],
                [
                    406.2347817420959,
                    231.46828007698056
                ],
                [
                    398.02480745315546,
                    231.46828007698056
                ]
            ],
            "group_id": 28,
            "description": null,
            "difficult": false,
            "shape_type": "rectangle",
            "flags": {},
            "attributes": {},
            "kie_linking": []
        },
        {
            "label": "corner",
            "score": 0.780139684677124,
            "points": [
                [
                    344.19298791885376,
                    257.860728263855
                ],
                [
                    353.85009145736694,
                    257.860728263855
                ],
                [
                    353.85009145736694,
                    267.7257671356201
                ],
                [
                    344.19298791885376,
                    267.7257671356201
                ]
            ],
            "group_id": 29,
            "description": null,
            "difficult": false,
            "shape_type": "rectangle",
            "flags": {},
            "attributes": {},
            "kie_linking": []
        },
        {
            "label": "corner",
            "score": 0.7513805031776428,
            "points": [
                [
                    246.0702698230743,
                    358.9212055206299
                ],
                [
                    254.53725600242612,
                    358.9212055206299
                ],
                [
                    254.53725600242612,
                    367.507303237915
                ],
                [
                    246.0702698230743,
                    367.507303237915
                ]
            ],
            "group_id": 30,
            "description": null,
            "difficult": false,
            "shape_type": "rectangle",
            "flags": {},
            "attributes": {},
            "kie_linking": []
        },
        {
            "label": "corner",
            "score": 0.7339452505111694,
            "points": [
                [
                    271.70213985443115,
                    359.2384023666382
                ],
                [
                    280.4572501182556,
                    359.2384023666382
                ],
                [
                    280.4572501182556,
                    368.23603153228754
                ],
                [
                    271.70213985443115,
                    368.23603153228754
                ]
            ],
            "group_id": 31,
            "description": null,
            "difficult": false,
            "shape_type": "rectangle",
            "flags": {},
            "attributes": {},
            "kie_linking": []
        },
        {
            "label": "corner",
            "score": 0.7193460464477539,
            "points": [
                [
                    145.2793447971344,
                    359.19049739837646
                ],
                [
                    154.7238700389862,
                    359.19049739837646
                ],
                [
                    154.7238700389862,
                    368.20357418060297
                ],
                [
                    145.2793447971344,
                    368.20357418060297
                ]
            ],
            "group_id": 32,
            "description": null,
            "difficult": false,
            "shape_type": "rectangle",
            "flags": {},
            "attributes": {},
            "kie_linking": []
        },
        {
            "label": "corner",
            "score": 0.7159426808357239,
            "points": [
                [
                    142.49406576156616,
                    129.52678966522217
                ],
                [
                    152.07809686660767,
                    129.52678966522217
                ],
                [
                    152.07809686660767,
                    138.30146980285645
                ],
                [
                    142.49406576156616,
                    138.30146980285645
                ]
            ],
            "group_id": 33,
            "description": null,
            "difficult": false,
            "shape_type": "rectangle",
            "flags": {},
            "attributes": {},
            "kie_linking": []
        },
        {
            "label": "corner",
            "score": 0.6253319382667542,
            "points": [
                [
                    367.3021883964538,
                    177.73717379570007
                ],
                [
                    376.50818681716913,
                    177.73717379570007
                ],
                [
                    376.50818681716913,
                    186.43261981010434
                ],
                [
                    367.3021883964538,
                    186.43261981010434
                ]
            ],
            "group_id": 34,
            "description": null,
            "difficult": false,
            "shape_type": "rectangle",
            "flags": {},
            "attributes": {},
            "kie_linking": []
        },
        {
            "label": "corner",
            "score": 0.5472956299781799,
            "points": [
                [
                    321.84666538238525,
                    157.24962043762207
                ],
                [
                    331.19377517700195,
                    157.24962043762207
                ],
                [
                    331.19377517700195,
                    166.58861589431763
                ],
                [
                    321.84666538238525,
                    166.58861589431763
                ]
            ],
            "group_id": 35,
            "description": null,
            "difficult": false,
            "shape_type": "rectangle",
            "flags": {},
            "attributes": {},
            "kie_linking": []
        },
        {
            "label": "corner",
            "score": 0.5110867619514465,
            "points": [
                [
                    286.39631628990173,
                    222.91520380973813
                ],
                [
                    294.9664022922516,
                    222.91520380973813
                ],
                [
                    294.9664022922516,
                    231.6936156749725
                ],
                [
                    286.39631628990173,
                    231.6936156749725
                ]
            ],
            "group_id": 36,
            "description": null,
            "difficult": false,
            "shape_type": "rectangle",
            "flags": {},
            "attributes": {},
            "kie_linking": []
        },
        {
            "label": "corner",
            "score": 0.4786616265773773,
            "points": [
                [
                    520.2676553726196,
                    177.60747456550598
                ],
                [
                    529.84543800354,
                    177.60747456550598
                ],
                [
                    529.84543800354,
                    186.52712798118588
                ],
                [
                    520.2676553726196,
                    186.52712798118588
                ]
            ],
            "group_id": 37,
            "description": null,
            "difficult": false,
            "shape_type": "rectangle",
            "flags": {},
            "attributes": {},
            "kie_linking": []
        },
        {
            "label": "corner",
            "score": 0.4613744020462036,
            "points": [
                [
                    519.9981031417847,
                    156.87876915931702
                ],
                [
                    530.0939016342163,
                    156.87876915931702
                ],
                [
                    530.0939016342163,
                    166.35050129890442
                ],
                [
                    519.9981031417847,
                    166.35050129890442
                ]
            ],
            "group_id": 38,
            "description": null,
            "difficult": false,
            "shape_type": "rectangle",
            "flags": {},
            "attributes": {},
            "kie_linking": []
        },
        {
            "label": "corner",
            "score": 0.29266422986984253,
            "points": [
                [
                    271.0982291698456,
                    413.0503482818603
                ],
                [
                    281.2422363758087,
                    413.0503482818603
                ],
                [
                    281.2422363758087,
                    422.59645462036127
                ],
                [
                    271.0982291698456,
                    422.59645462036127
                ]
            ],
            "group_id": 39,
            "description": null,
            "difficult": false,
            "shape_type": "rectangle",
            "flags": {},
            "attributes": {},
            "kie_linking": []
        },
        {
            "label": "corner",
            "score": 0.27838724851608276,
            "points": [
                [
                    343.7924780845642,
                    413.2575025558471
                ],
                [
                    354.0061731338501,
                    413.2575025558471
                ],
                [
                    354.0061731338501,
                    422.50151252746576
                ],
                [
                    343.7924780845642,
                    422.50151252746576
                ]
            ],
            "group_id": 40,
            "description": null,
            "difficult": false,
            "shape_type": "rectangle",
            "flags": {},
            "attributes": {},
            "kie_linking": []
        },
        {
            "label": "corner",
            "score": 0.15652519464492798,
            "points": [
                [
                    76.66283816099167,
                    315.85446548461914
                ],
                [
                    86.8754158616066,
                    315.85446548461914
                ],
                [
                    86.8754158616066,
                    326.03062629699707
                ],
                [
                    76.66283816099167,
                    326.03062629699707
                ]
            ],
            "group_id": 41,
            "description": null,
            "difficult": false,
            "shape_type": "rectangle",
            "flags": {},
            "attributes": {},
            "kie_linking": []
        },
        {
            "label": "corner",
            "score": 0.12081784009933472,
            "points": [
                [
                    348.544659614563,
                    25.775075078010556
                ],
                [
                    358.84236192703247,
                    25.775075078010556
                ],
                [
                    358.84236192703247,
                    36.879806876182556
                ],
                [
                    348.544659614563,
                    36.879806876182556
                ]
            ],
            "group_id": 42,
            "description": null,
            "difficult": false,
            "shape_type": "rectangle",
            "flags": {},
            "attributes": {},
            "kie_linking": []
        }
    ],
    "imagePath": "1450.png",
    "imageData": null,
    "imageHeight": 491,
    "imageWidth": 728
}