{
  "version": "2.4.0",
  "flags": {},
  "shapes": [
    {
      "kie_linking": [],
      "label": "Voltage_2",
      "score": 0.9776843786239624,
      "points": [
        [
          350.15100955963135,
          78.38445886969566
        ],
        [
          392.89683759212494,
          78.38445886969566
        ],
        [
          392.89683759212494,
          112.43821516633034
        ],
        [
          350.15100955963135,
          112.43821516633034
        ]
      ],
      "group_id": 0,
      "description": null,
      "difficult": false,
      "shape_type": "rectangle",
      "flags": {},
      "attributes": {}
    },
    {
      "kie_linking": [],
      "label": "Positive",
      "score": 0.9999849796295166,
      "points": [
        [
          371.0,
          110.0
        ]
      ],
      "group_id": 0,
      "description": null,
      "difficult": false,
      "shape_type": "point",
      "flags": {},
      "attributes": {}
    },
    {
      "kie_linking": [],
      "label": "Negative",
      "score": 0.9999918937683105,
      "points": [
        [
          371.0,
          81.0
        ]
      ],
      "group_id": 0,
      "description": null,
      "difficult": false,
      "shape_type": "point",
      "flags": {},
      "attributes": {}
    },
    {
      "kie_linking": [],
      "label": "resistor",
      "score": 0.9632449746131897,
      "points": [
        [
          301.60722851753235,
          361.3867598772049
        ],
        [
          319.9909085035324,
          361.3867598772049
        ],
        [
          319.9909085035324,
          402.8036940097809
        ],
        [
          301.60722851753235,
          402.8036940097809
        ]
      ],
      "group_id": 1,
      "description": null,
      "difficult": false,
      "shape_type": "rectangle",
      "flags": {},
      "attributes": {}
    },
    {
      "kie_linking": [],
      "label": "Positive",
      "score": 0.9998332858085632,
      "points": [
        [
          309.0,
          362.0
        ]
      ],
      "group_id": 1,
      "description": null,
      "difficult": false,
      "shape_type": "point",
      "flags": {},
      "attributes": {}
    },
    {
      "kie_linking": [],
      "label": "Negative",
      "score": 0.9997503757476807,
      "points": [
        [
          309.0,
          399.0
        ]
      ],
      "group_id": 1,
      "description": null,
      "difficult": false,
      "shape_type": "point",
      "flags": {},
      "attributes": {}
    },
    {
      "kie_linking": [],
      "label": "capacitor",
      "score": 0.9601097106933594,
      "points": [
        [
          517.0152169466019,
          274.43096935749054
        ],
        [
          531.443207859993,
          274.43096935749054
        ],
        [
          531.443207859993,
          307.1949368715286
        ],
        [
          517.0152169466019,
          307.1949368715286
        ]
      ],
      "group_id": 2,
      "description": null,
      "difficult": false,
      "shape_type": "rectangle",
      "flags": {},
      "attributes": {}
    },
    {
      "kie_linking": [],
      "label": "Positive",
      "score": 0.9997109770774841,
      "points": [
        [
          518.0,
          290.0
        ]
      ],
      "group_id": 2,
      "description": null,
      "difficult": false,
      "shape_type": "point",
      "flags": {},
      "attributes": {}
    },
    {
      "kie_linking": [],
      "label": "Negative",
      "score": 0.9997974038124084,
      "points": [
        [
          527.0,
          289.0
        ]
      ],
      "group_id": 2,
      "description": null,
      "difficult": false,
      "shape_type": "point",
      "flags": {},
      "attributes": {}
    },
    {
      "kie_linking": [],
      "label": "Voltage_1",
      "score": 0.954483151435852,
      "points": [
        [
          38.438156470656395,
          323.5615700483322
        ],
        [
          93.14596056938171,
          323.5615700483322
        ],
        [
          93.14596056938171,
          381.6743975877762
        ],
        [
          38.438156470656395,
          381.6743975877762
        ]
      ],
      "group_id": 3,
      "description": null,
      "difficult": false,
      "shape_type": "rectangle",
      "flags": {},
      "attributes": {}
    },
    {
      "kie_linking": [],
      "label": "Positive",
      "score": 0.9997693300247192,
      "points": [
        [
          64.0,
          326.0
        ]
      ],
      "group_id": 3,
      "description": null,
      "difficult": false,
      "shape_type": "point",
      "flags": {},
      "attributes": {}
    },
    {
      "kie_linking": [],
      "label": "Negative",
      "score": 0.998432457447052,
      "points": [
        [
          64.0,
          376.0
        ]
      ],
      "group_id": 3,
      "description": null,
      "difficult": false,
      "shape_type": "point",
      "flags": {},
      "attributes": {}
    },
    {
      "kie_linking": [],
      "label": "resistor",
      "score": 0.9542793035507202,
      "points": [
        [
          423.9401799440384,
          349.6622198820114
        ],
        [
          441.85547292232513,
          349.6622198820114
        ],
        [
          441.85547292232513,
          390.54353535175323
        ],
        [
          423.9401799440384,
          390.54353535175323
        ]
      ],
      "group_id": 4,
      "description": null,
      "difficult": false,
      "shape_type": "rectangle",
      "flags": {},
      "attributes": {}
    },
    {
      "kie_linking": [],
      "label": "Positive",
      "score": 0.9995349049568176,
      "points": [
        [
          431.0,
          350.0
        ]
      ],
      "group_id": 4,
      "description": null,
      "difficult": false,
      "shape_type": "point",
      "flags": {},
      "attributes": {}
    },
    {
      "kie_linking": [],
      "label": "Negative",
      "score": 0.9998483657836914,
      "points": [
        [
          431.0,
          387.0
        ]
      ],
      "group_id": 4,
      "description": null,
      "difficult": false,
      "shape_type": "point",
      "flags": {},
      "attributes": {}
    },
    {
      "kie_linking": [],
      "label": "capacitor",
      "score": 0.9490084648132324,
      "points": [
        [
          235.95238402485847,
          250.115480273962
        ],
        [
          250.29716119170186,
          250.115480273962
        ],
        [
          250.29716119170186,
          282.5452083349228
        ],
        [
          235.95238402485847,
          282.5452083349228
        ]
      ],
      "group_id": 5,
      "description": null,
      "difficult": false,
      "shape_type": "rectangle",
      "flags": {},
      "attributes": {}
    },
    {
      "kie_linking": [],
      "label": "Positive",
      "score": 0.9999542236328125,
      "points": [
        [
          237.0,
          266.0
        ]
      ],
      "group_id": 5,
      "description": null,
      "difficult": false,
      "shape_type": "point",
      "flags": {},
      "attributes": {}
    },
    {
      "kie_linking": [],
      "label": "Negative",
      "score": 0.999991238117218,
      "points": [
        [
          246.0,
          266.0
        ]
      ],
      "group_id": 5,
      "description": null,
      "difficult": false,
      "shape_type": "point",
      "flags": {},
      "attributes": {}
    },
    {
      "kie_linking": [],
      "label": "npn",
      "score": 0.9467211961746216,
      "points": [
        [
          414.7047656774521,
          244.77204531431195
        ],
        [
          437.38029301166534,
          244.77204531431195
        ],
        [
          437.38029301166534,
          287.22388058900833
        ],
        [
          414.7047656774521,
          287.22388058900833
        ]
      ],
      "group_id": 6,
      "description": null,
      "difficult": false,
      "shape_type": "rectangle",
      "flags": {},
      "attributes": {}
    },
    {
      "kie_linking": [],
      "label": "Base",
      "score": 0.9998332262039185,
      "points": [
        [
          416.0,
          265.0
        ]
      ],
      "group_id": 6,
      "description": null,
      "difficult": false,
      "shape_type": "point",
      "flags": {},
      "attributes": {}
    },
    {
      "kie_linking": [],
      "label": "Emitter",
      "score": 0.9999626874923706,
      "points": [
        [
          432.0,
          282.0
        ]
      ],
      "group_id": 6,
      "description": null,
      "difficult": false,
      "shape_type": "point",
      "flags": {},
      "attributes": {}
    },
    {
      "kie_linking": [],
      "label": "Collect",
      "score": 0.9992165565490723,
      "points": [
        [
          431.0,
          247.0
        ]
      ],
      "group_id": 6,
      "description": null,
      "difficult": false,
      "shape_type": "point",
      "flags": {},
      "attributes": {}
    },
    {
      "kie_linking": [],
      "label": "resistor",
      "score": 0.9441556930541992,
      "points": [
        [
          301.7245924472809,
          190.81592172384262
        ],
        [
          319.9579727649689,
          190.81592172384262
        ],
        [
          319.9579727649689,
          231.26654654741287
        ],
        [
          301.7245924472809,
          231.26654654741287
        ]
      ],
      "group_id": 7,
      "description": null,
      "difficult": false,
      "shape_type": "rectangle",
      "flags": {},
      "attributes": {}
    },
    {
      "kie_linking": [],
      "label": "Positive",
      "score": 0.9998852014541626,
      "points": [
        [
          308.0,
          191.0
        ]
      ],
      "group_id": 7,
      "description": null,
      "difficult": false,
      "shape_type": "point",
      "flags": {},
      "attributes": {}
    },
    {
      "kie_linking": [],
      "label": "Negative",
      "score": 0.9999487400054932,
      "points": [
        [
          308.0,
          227.0
        ]
      ],
      "group_id": 7,
      "description": null,
      "difficult": false,
      "shape_type": "point",
      "flags": {},
      "attributes": {}
    },
    {
      "kie_linking": [],
      "label": "resistor",
      "score": 0.9437670707702637,
      "points": [
        [
          607.4945485591888,
          313.78023862838745
        ],
        [
          625.292477607727,
          313.78023862838745
        ],
        [
          625.292477607727,
          353.6880552768707
        ],
        [
          607.4945485591888,
          353.6880552768707
        ]
      ],
      "group_id": 8,
      "description": null,
      "difficult": false,
      "shape_type": "rectangle",
      "flags": {},
      "attributes": {}
    },
    {
      "kie_linking": [],
      "label": "Positive",
      "score": 0.99944007396698,
      "points": [
        [
          614.0,
          314.0
        ]
      ],
      "group_id": 8,
      "description": null,
      "difficult": false,
      "shape_type": "point",
      "flags": {},
      "attributes": {}
    },
    {
      "kie_linking": [],
      "label": "Negative",
      "score": 0.9999080896377563,
      "points": [
        [
          614.0,
          350.0
        ]
      ],
      "group_id": 8,
      "description": null,
      "difficult": false,
      "shape_type": "point",
      "flags": {},
      "attributes": {}
    },
    {
      "kie_linking": [],
      "label": "capacitor",
      "score": 0.9432122707366943,
      "points": [
        [
          697.4420991539955,
          326.46326690912247
        ],
        [
          730.0489661097527,
          326.46326690912247
        ],
        [
          730.0489661097527,
          341.7232981324196
        ],
        [
          697.4420991539955,
          341.7232981324196
        ]
      ],
      "group_id": 9,
      "description": null,
      "difficult": false,
      "shape_type": "rectangle",
      "flags": {},
      "attributes": {}
    },
    {
      "kie_linking": [],
      "label": "Positive",
      "score": 0.999845564365387,
      "points": [
        [
          712.0,
          328.0
        ]
      ],
      "group_id": 9,
      "description": null,
      "difficult": false,
      "shape_type": "point",
      "flags": {},
      "attributes": {}
    },
    {
      "kie_linking": [],
      "label": "Negative",
      "score": 0.9999887347221375,
      "points": [
        [
          712.0,
          337.0
        ]
      ],
      "group_id": 9,
      "description": null,
      "difficult": false,
      "shape_type": "point",
      "flags": {},
      "attributes": {}
    },
    {
      "kie_linking": [],
      "label": "gnd",
      "score": 0.9394081234931946,
      "points": [
        [
          698.5890692472458,
          410.18635153770447
        ],
        [
          728.8938349485397,
          410.18635153770447
        ],
        [
          728.8938349485397,
          424.7462797164917
        ],
        [
          698.5890692472458,
          424.7462797164917
        ]
      ],
      "group_id": 10,
      "description": null,
      "difficult": false,
      "shape_type": "rectangle",
      "flags": {},
      "attributes": {}
    },
    {
      "kie_linking": [],
      "label": "port",
      "score": 0.9997227191925049,
      "points": [
        [
          712.0,
          411.0
        ]
      ],
      "group_id": 10,
      "description": null,
      "difficult": false,
      "shape_type": "point",
      "flags": {},
      "attributes": {}
    },
    {
      "kie_linking": [],
      "label": "resistor",
      "score": 0.9352598786354065,
      "points": [
        [
          124.72688898444174,
          255.9106886386871
        ],
        [
          164.8586006462574,
          255.9106886386871
        ],
        [
          164.8586006462574,
          274.43806171417236
        ],
        [
          124.72688898444174,
          274.43806171417236
        ]
      ],
      "group_id": 11,
      "description": null,
      "difficult": false,
      "shape_type": "rectangle",
      "flags": {},
      "attributes": {}
    },
    {
      "kie_linking": [],
      "label": "Positive",
      "score": 0.9966886043548584,
      "points": [
        [
          125.0,
          264.0
        ]
      ],
      "group_id": 11,
      "description": null,
      "difficult": false,
      "shape_type": "point",
      "flags": {},
      "attributes": {}
    },
    {
      "kie_linking": [],
      "label": "Negative",
      "score": 0.9993883967399597,
      "points": [
        [
          161.0,
          264.0
        ]
      ],
      "group_id": 11,
      "description": null,
      "difficult": false,
      "shape_type": "point",
      "flags": {},
      "attributes": {}
    },
    {
      "kie_linking": [],
      "label": "gnd",
      "score": 0.9321111440658569,
      "points": [
        [
          356.3672901690006,
          471.0712218284607
        ],
        [
          386.39487102627754,
          471.0712218284607
        ],
        [
          386.39487102627754,
          485.13623952865595
        ],
        [
          356.3672901690006,
          485.13623952865595
        ]
      ],
      "group_id": 12,
      "description": null,
      "difficult": false,
      "shape_type": "rectangle",
      "flags": {},
      "attributes": {}
    },
    {
      "kie_linking": [],
      "label": "port",
      "score": 0.9993712902069092,
      "points": [
        [
          370.0,
          472.0
        ]
      ],
      "group_id": 12,
      "description": null,
      "difficult": false,
      "shape_type": "point",
      "flags": {},
      "attributes": {}
    },
    {
      "kie_linking": [],
      "label": "gnd",
      "score": 0.9193350076675415,
      "points": [
        [
          51.13534517586231,
          422.0909208059311
        ],
        [
          80.6870823353529,
          422.0909208059311
        ],
        [
          80.6870823353529,
          436.5606886148453
        ],
        [
          51.13534517586231,
          436.5606886148453
        ]
      ],
      "group_id": 13,
      "description": null,
      "difficult": false,
      "shape_type": "rectangle",
      "flags": {},
      "attributes": {}
    },
    {
      "kie_linking": [],
      "label": "port",
      "score": 0.9961364269256592,
      "points": [
        [
          65.0,
          423.0
        ]
      ],
      "group_id": 13,
      "description": null,
      "difficult": false,
      "shape_type": "point",
      "flags": {},
      "attributes": {}
    },
    {
      "kie_linking": [],
      "label": "gnd",
      "score": 0.8811115622520447,
      "points": [
        [
          355.67896723747253,
          22.07922287285328
        ],
        [
          386.6647934913635,
          22.07922287285328
        ],
        [
          386.6647934913635,
          38.87576945126057
        ],
        [
          355.67896723747253,
          38.87576945126057
        ]
      ],
      "group_id": 14,
      "description": null,
      "difficult": false,
      "shape_type": "rectangle",
      "flags": {},
      "attributes": {}
    },
    {
      "kie_linking": [],
      "label": "port",
      "score": 0.9991481304168701,
      "points": [
        [
          370.0,
          37.0
        ]
      ],
      "group_id": 14,
      "description": null,
      "difficult": false,
      "shape_type": "point",
      "flags": {},
      "attributes": {}
    },
    {
      "kie_linking": [],
      "label": "corner",
      "score": 0.8724533319473267,
      "points": [
        [
          303.44861805438995,
          259.8133307695389
        ],
        [
          317.61438608169556,
          259.8133307695389
        ],
        [
          317.61438608169556,
          274.150772690773
        ],
        [
          303.44861805438995,
          274.150772690773
        ]
      ],
      "group_id": 15,
      "description": null,
      "difficult": false,
      "shape_type": "rectangle",
      "flags": {},
      "attributes": {}
    },
    {
      "kie_linking": [],
      "label": "corner",
      "score": 0.8453563451766968,
      "points": [
        [
          364.40322175621986,
          430.0003558397293
        ],
        [
          379.29377034306526,
          430.0003558397293
        ],
        [
          379.29377034306526,
          444.80200707912445
        ],
        [
          364.40322175621986,
          444.80200707912445
        ]
      ],
      "group_id": 16,
      "description": null,
      "difficult": false,
      "shape_type": "rectangle",
      "flags": {},
      "attributes": {}
    },
    {
      "kie_linking": [],
      "label": "corner",
      "score": 0.742698073387146,
      "points": [
        [
          705.9906721115112,
          381.25186800956726
        ],
        [
          720.7722121477127,
          381.25186800956726
        ],
        [
          720.7722121477127,
          396.31661653518677
        ],
        [
          705.9906721115112,
          396.31661653518677
        ]
      ],
      "group_id": 17,
      "description": null,
      "difficult": false,
      "shape_type": "rectangle",
      "flags": {},
      "attributes": {}
    },
    {
      "kie_linking": [],
      "label": "corner",
      "score": 0.6198578476905823,
      "points": [
        [
          364.88125145435333,
          137.6650235056877
        ],
        [
          378.9222717285156,
          137.6650235056877
        ],
        [
          378.9222717285156,
          151.9056984782219
        ],
        [
          364.88125145435333,
          151.9056984782219
        ]
      ],
      "group_id": 18,
      "description": null,
      "difficult": false,
      "shape_type": "rectangle",
      "flags": {},
      "attributes": {}
    },
    {
      "kie_linking": [],
      "label": "corner",
      "score": null,
      "points": [
        [
          428.5610932475885,
          287.459807073955
        ],
        [
          439.4935691318328,
          287.459807073955
        ],
        [
          439.4935691318328,
          299.0353697749196
        ],
        [
          428.5610932475885,
          299.0353697749196
        ]
      ],
      "group_id": null,
      "description": "",
      "difficult": false,
      "shape_type": "rectangle",
      "flags": {},
      "attributes": {}
    },
    {
      "label": "corner",
      "score": null,
      "points": [
        [
          610.5386740331492,
          284.5303867403315
        ],
        [
          622.6933701657459,
          284.5303867403315
        ],
        [
          622.6933701657459,
          298.89502762430936
        ],
        [
          610.5386740331492,
          298.89502762430936
        ]
      ],
      "group_id": null,
      "description": "",
      "difficult": false,
      "shape_type": "rectangle",
      "flags": {},
      "attributes": {},
      "kie_linking": []
    }
  ],
  "imagePath": "1510.png",
  "imageData": null,
  "imageHeight": 510,
  "imageWidth": 815,
  "text": ""
}