{
    "version": "5.1.1",
    "flags": {},
    "shapes": [
        {
            "label": "capacitor",
            "points": [
                [
                    427.8197,
                    127.964
                ],
                [
                    466.3989,
                    127.964
                ],
                [
                    466.3989,
                    158.7652
                ],
                [
                    427.8197,
                    158.7652
                ]
            ],
            "group_id": 0,
            "shape_type": "rectangle",
            "flags": {}
        },
        {
            "label": "capacitor",
            "points": [
                [
                    682.9146,
                    127.4121
                ],
                [
                    721.5082,
                    127.4121
                ],
                [
                    721.5082,
                    158.2089
                ],
                [
                    682.9146,
                    158.2089
                ]
            ],
            "group_id": 1,
            "shape_type": "rectangle",
            "flags": {}
        },
        {
            "label": "capacitor",
            "points": [
                [
                    738.3851,
                    70.527
                ],
                [
                    773.7705,
                    70.527
                ],
                [
                    773.7705,
                    111.6799
                ],
                [
                    738.3851,
                    111.6799
                ]
            ],
            "group_id": 2,
            "shape_type": "rectangle",
            "flags": {}
        },
        {
            "label": "capacitor",
            "points": [
                [
                    592.9638,
                    69.8197
                ],
                [
                    628.3597,
                    69.8197
                ],
                [
                    628.3597,
                    110.9694
                ],
                [
                    592.9638,
                    110.9694
                ]
            ],
            "group_id": 3,
            "shape_type": "rectangle",
            "flags": {}
        },
        {
            "label": "capacitor",
            "points": [
                [
                    341.323,
                    69.0975
                ],
                [
                    376.713,
                    69.0975
                ],
                [
                    376.713,
                    110.2491
                ],
                [
                    341.323,
                    110.2491
                ]
            ],
            "group_id": 4,
            "shape_type": "rectangle",
            "flags": {}
        },
        {
            "label": "capacitor",
            "points": [
                [
                    194.413,
                    67.8519
                ],
                [
                    229.8054,
                    67.8519
                ],
                [
                    229.8054,
                    109.0
                ],
                [
                    194.413,
                    109.0
                ]
            ],
            "group_id": 5,
            "shape_type": "rectangle",
            "flags": {}
        },
        {
            "label": "capacitor",
            "points": [
                [
                    93.2158,
                    272.8402
                ],
                [
                    128.61,
                    272.8402
                ],
                [
                    128.61,
                    313.9955
                ],
                [
                    93.2158,
                    313.9955
                ]
            ],
            "group_id": 6,
            "shape_type": "rectangle",
            "flags": {}
        },
        {
            "label": "Diso_amp",
            "points": [
                [
                    391.6865,
                    259.9723
                ],
                [
                    512.9051,
                    259.9723
                ],
                [
                    512.9051,
                    394.7978
                ],
                [
                    391.6865,
                    394.7978
                ]
            ],
            "group_id": 7,
            "shape_type": "rectangle",
            "flags": {}
        },
        {
            "label": "capacitor",
            "points": [
                [
                    435.8069,
                    220.568
                ],
                [
                    471.21,
                    220.568
                ],
                [
                    471.21,
                    261.7137
                ],
                [
                    435.8069,
                    261.7137
                ]
            ],
            "group_id": 8,
            "shape_type": "rectangle",
            "flags": {}
        },
        {
            "label": "capacitor",
            "points": [
                [
                    284.165,
                    126.9003
                ],
                [
                    322.7567,
                    126.9003
                ],
                [
                    322.7567,
                    157.6984
                ],
                [
                    284.165,
                    157.6984
                ]
            ],
            "group_id": 9,
            "shape_type": "rectangle",
            "flags": {}
        }
    ],
    "imagePath": "756.png",
    "imageData": null,
    "imageHeight": 400,
    "imageWidth": 956
}